encode_videos.py
jelly_coder/__init__.py
jelly_coder/__main__.py
jelly_coder/cli.py
jelly_coder/core.py
jellycoder-1.1.0.dist-info/licenses/LICENSE
jellycoder-1.1.0.dist-info/METADATA
jellycoder-1.1.0.dist-info/WHEEL
jellycoder-1.1.0.dist-info/entry_points.txt
jellycoder-1.1.0.dist-info/top_level.txt
jellycoder-1.1.0.dist-info/RECORD
