Metadata-Version: 2.4
Name: jellycoder
Version: 1.1.0
Summary: Video reduction tool
Author: 0x78f1935
License:                     GNU GENERAL PUBLIC LICENSE
Project-URL: Homepage, https://github.com/0x78f1935/JellyCoder
Project-URL: Repository, https://github.com/0x78f1935/JellyCoder
Project-URL: Issues, https://github.com/0x78f1935/JellyCoder/issues
Keywords: ffmpeg,video,encoding,compression
Classifier: Development Status :: 4 - Beta
Classifier: Intended Audience :: Developers
Classifier: License :: OSI Approved :: MIT License
Classifier: Programming Language :: Python :: 3
Classifier: Programming Language :: Python :: 3.10
Classifier: Programming Language :: Python :: 3.11
Classifier: Programming Language :: Python :: 3.12
Classifier: Operating System :: OS Independent
Classifier: Topic :: Multimedia :: Video
Requires-Python: >=3.10
License-File: LICENSE
Provides-Extra: dev
Requires-Dist: pytest; extra == "dev"
Requires-Dist: pytest-cov; extra == "dev"
Requires-Dist: flake8; extra == "dev"
Requires-Dist: build; extra == "dev"
Requires-Dist: twine; extra == "dev"
Dynamic: license-file
